workbench_jupyterlab/__init__.py
workbench_jupyterlab/_version.py
workbench_jupyterlab/constants.py
workbench_jupyterlab/handlers.py
workbench_jupyterlab/network.py
workbench_jupyterlab/process.py
workbench_jupyterlab/proxiedServersProvider.py
workbench_jupyterlab/labextension/build_log.json
workbench_jupyterlab/labextension/package.json
workbench_jupyterlab/labextension/schemas/workbench_jupyterlab/package.json.orig
workbench_jupyterlab/labextension/schemas/workbench_jupyterlab/plugin.json
workbench_jupyterlab/labextension/static/lib_index_js.67179098403118486ca2.js
workbench_jupyterlab/labextension/static/lib_index_js.67179098403118486ca2.js.map
workbench_jupyterlab/labextension/static/remoteEntry.fd1ba3d0128ba8dbc63f.js
workbench_jupyterlab/labextension/static/remoteEntry.fd1ba3d0128ba8dbc63f.js.map
workbench_jupyterlab/labextension/static/style.js
workbench_jupyterlab/labextension/static/style_index_js.6d628d3968c013134abc.js
workbench_jupyterlab/labextension/static/style_index_js.6d628d3968c013134abc.js.map
workbench_jupyterlab/labextension/static/vendors-node_modules_css-loader_dist_runtime_api_js-node_modules_css-loader_dist_runtime_cssW-72eba1.3b7d3b09f767b5bc943b.js
workbench_jupyterlab/labextension/static/vendors-node_modules_css-loader_dist_runtime_api_js-node_modules_css-loader_dist_runtime_cssW-72eba1.3b7d3b09f767b5bc943b.js.map
workbench_jupyterlab-1.1.738.data/data/etc/jupyter/jupyter_server_config.d/workbench_jupyterlab.json
workbench_jupyterlab-1.1.738.data/data/share/jupyter/labextensions/workbench_jupyterlab/build_log.json
workbench_jupyterlab-1.1.738.data/data/share/jupyter/labextensions/workbench_jupyterlab/install.json
workbench_jupyterlab-1.1.738.data/data/share/jupyter/labextensions/workbench_jupyterlab/package.json
workbench_jupyterlab-1.1.738.data/data/share/jupyter/labextensions/workbench_jupyterlab/schemas/workbench_jupyterlab/package.json.orig
workbench_jupyterlab-1.1.738.dist-info/METADATA
workbench_jupyterlab-1.1.738.dist-info/WHEEL
workbench_jupyterlab-1.1.738.dist-info/top_level.txt
workbench_jupyterlab-1.1.738.dist-info/RECORD
