Metadata-Version: 2.1
Name: workbench_jupyterlab
Version: 1.1.738
Summary: Enhance experience of running JupyterLab in Posit Workbench.
Home-page: https://docs.posit.co/ide/server-pro/user/jupyter-lab/guide/posit-workbench-extension.html
Author: Posit Software, PBC
Author-email: 
Keywords: Jupyter,JupyterLab,JupyterLab3
Platform: Linux
Platform: Mac OS X
Platform: Windows
Classifier: License :: OSI Approved :: BSD License
Classifier: Programming Language :: Python
Classifier: Programming Language :: Python :: 3
Classifier: Programming Language :: Python :: 3.7
Classifier: Programming Language :: Python :: 3.8
Classifier: Programming Language :: Python :: 3.9
Classifier: Programming Language :: Python :: 3.10
Classifier: Programming Language :: Python :: 3.11
Classifier: Framework :: Jupyter
Requires-Python: >=3.7
Requires-Dist: jupyter-server <2,>=1.6
Requires-Dist: jupyter-server-proxy
